<?xml version="1.0" encoding="utf-8"?>
<LanguageData>

  <!-- Demon privates -->

  <DemonTentaclePenis.label>demon tentacles</DemonTentaclePenis.label>
  <DemonTentaclePenis.labelNoun>demon tentacles</DemonTentaclePenis.labelNoun>
  <DemonTentaclePenis.description>Tentacles capable of reaching corners of the body you never thought possible.</DemonTentaclePenis.description>
  <DemonTentaclePenis.stages.0.label>Micro</DemonTentaclePenis.stages.0.label>
  <DemonTentaclePenis.stages.1.label>Small</DemonTentaclePenis.stages.1.label>
  <DemonTentaclePenis.stages.2.label>Average</DemonTentaclePenis.stages.2.label>
  <DemonTentaclePenis.stages.3.label>Large</DemonTentaclePenis.stages.3.label>
  <DemonTentaclePenis.stages.4.label>Huge</DemonTentaclePenis.stages.4.label>
  <DemonTentaclePenis.stages.5.label>Towering</DemonTentaclePenis.stages.5.label>

  <DemonPenis.label>demon penis</DemonPenis.label>
  <DemonPenis.labelNoun>a demon penis</DemonPenis.labelNoun>
  <DemonPenis.description>A large, daunting mass that can cause its lovers to succumb to debauchery.</DemonPenis.description>
  <DemonPenis.stages.0.label>Micro</DemonPenis.stages.0.label>
  <DemonPenis.stages.1.label>Small</DemonPenis.stages.1.label>
  <DemonPenis.stages.2.label>Average</DemonPenis.stages.2.label>
  <DemonPenis.stages.3.label>Large</DemonPenis.stages.3.label>
  <DemonPenis.stages.4.label>Huge</DemonPenis.stages.4.label>
  <DemonPenis.stages.5.label>Towering</DemonPenis.stages.5.label>

  <DemonVagina.label>demon vagina</DemonVagina.label>
  <DemonVagina.labelNoun>a demon vagina</DemonVagina.labelNoun>
  <DemonVagina.description>A tight vagina that can send its lovers to heaven.</DemonVagina.description>
  <DemonVagina.stages.0.label>Micro</DemonVagina.stages.0.label>
  <DemonVagina.stages.1.label>Tight</DemonVagina.stages.1.label>
  <DemonVagina.stages.2.label>Average</DemonVagina.stages.2.label>
  <DemonVagina.stages.3.label>Accommodating</DemonVagina.stages.3.label>
  <DemonVagina.stages.4.label>Cavernous</DemonVagina.stages.4.label>
  <DemonVagina.stages.5.label>Abyssal</DemonVagina.stages.5.label>

  <DemonAnus.label>demon anus</DemonAnus.label>
  <DemonAnus.labelNoun>a demon anus</DemonAnus.labelNoun>
  <DemonAnus.description>A demon anus.</DemonAnus.description>
  <DemonAnus.stages.0.label>Micro</DemonAnus.stages.0.label>
  <DemonAnus.stages.1.label>Tight</DemonAnus.stages.1.label>
  <DemonAnus.stages.2.label>Average</DemonAnus.stages.2.label>
  <DemonAnus.stages.3.label>Accommodating</DemonAnus.stages.3.label>
  <DemonAnus.stages.4.label>Cavernous</DemonAnus.stages.4.label>
  <DemonAnus.stages.5.label>Abyssal</DemonAnus.stages.5.label>


</LanguageData>